{
  "filename": "new",
  "selectedId": 1,
  "selectedComponentId": "panel1576548838578",
  "structure": {
    "id": 1,
    "name": "uIdea",
    "children": [
      { "id": 1576548749824, "name": "颜值" },
      {
        "id": 1576548782645,
        "name": "才华",
        "children": [
          { "id": 1576548806777, "name": "图片" },
          { "id": 1576548838578, "name": "画布" }
        ]
      },
      { "id": 1576548768940, "name": "人品" }
    ]
  },
  "components": [
    {
      "type": "panel",
      "id": 1,
      "value": "column",
      "attrs": {
        "span": [1],
        "flex": "column",
        "backgroundColor": "#fffff",
        "padding": 10
      },
      "children": [
        {
          "id": 2,
          "value": "uIdea",
          "type": "text",
          "attrs": {
            "fontSize": 200,
            "color": "#000000",
            "textAlign": "center",
            "padding": 10,
            "verticalAlign": "center",
            "isTitle": true
          }
        }
      ]
    },
    {
      "type": "panel",
      "id": 1576548749824,
      "value": "column",
      "attrs": {
        "span": [1, 2],
        "flex": "column",
        "backgroundColor": "#fffff",
        "padding": 10
      },
      "children": [
        {
          "id": "text1576548749824",
          "value": "颜值",
          "type": "text",
          "attrs": {
            "fontSize": "$2",
            "color": "#000000",
            "textAlign": "left",
            "padding": 10,
            "verticalAlign": "center",
            "isTitle": true
          }
        },
        {
          "type": "panel",
          "id": "panel1576548749824",
          "value": "column",
          "attrs": {
            "span": [],
            "flex": "column",
            "backgroundColor": "#fffff",
            "padding": 10
          },
          "children": []
        }
      ]
    },
    {
      "type": "panel",
      "id": 1576548768940,
      "value": "column",
      "attrs": {
        "span": [1, 2],
        "flex": "column",
        "backgroundColor": "#fffff",
        "padding": 10
      },
      "children": [
        {
          "id": "text1576548768940",
          "value": "人品",
          "type": "text",
          "attrs": {
            "fontSize": "$2",
            "color": "#000000",
            "textAlign": "left",
            "padding": 10,
            "verticalAlign": "center",
            "isTitle": true
          }
        },
        {
          "type": "panel",
          "id": "panel1576548768940",
          "value": "column",
          "attrs": {
            "span": [],
            "flex": "column",
            "backgroundColor": "#fffff",
            "padding": 10
          },
          "children": []
        }
      ]
    },
    {
      "type": "panel",
      "id": 1576548782645,
      "value": "column",
      "attrs": {
        "span": [1, 2],
        "flex": "column",
        "backgroundColor": "#fffff",
        "padding": 10
      },
      "children": [
        {
          "id": "text1576548782645",
          "value": "才华",
          "type": "text",
          "attrs": {
            "fontSize": "$2",
            "color": "#000000",
            "textAlign": "left",
            "padding": 10,
            "verticalAlign": "center",
            "isTitle": true
          }
        },
        {
          "type": "panel",
          "id": "panel1576548782645",
          "value": "column",
          "attrs": {
            "span": [],
            "flex": "column",
            "backgroundColor": "#fffff",
            "padding": 10
          },
          "children": []
        }
      ]
    },
    {
      "type": "panel",
      "id": 1576548806777,
      "value": "column",
      "attrs": {
        "span": [1, 2],
        "flex": "column",
        "backgroundColor": "#fffff",
        "padding": 10
      },
      "children": [
        {
          "id": "text1576548806777",
          "value": "图片",
          "type": "text",
          "attrs": {
            "fontSize": "$2",
            "color": "#000000",
            "textAlign": "left",
            "padding": 10,
            "verticalAlign": "center",
            "isTitle": true
          }
        },
        {
          "type": "panel",
          "id": "panel1576548806777",
          "value": "column",
          "attrs": {
            "span": [1],
            "flex": "column",
            "backgroundColor": "#fffff",
            "padding": 10
          },
          "children": [
            {
              "type": "image",
              "id": 1576548812670,
              "value": "/static/example.3517664f.jpg",
              "attrs": { "displayMode": "scaleToFill", "padding": 10 }
            }
          ]
        }
      ]
    },
    {
      "type": "panel",
      "id": 1576548838578,
      "value": "column",
      "attrs": {
        "span": [1, 2],
        "flex": "column",
        "backgroundColor": "#fffff",
        "padding": 10
      },
      "children": [
        {
          "id": "text1576548838578",
          "value": "画布",
          "type": "text",
          "attrs": {
            "fontSize": "$2",
            "color": "#000000",
            "textAlign": "left",
            "padding": 10,
            "verticalAlign": "center",
            "isTitle": true
          }
        },
        {
          "type": "panel",
          "id": "panel1576548838578",
          "value": "column",
          "attrs": {
            "span": [1],
            "flex": "column",
            "backgroundColor": "#fffff",
            "padding": 10
          },
          "children": [
            {
              "type": "canvas",
              "id": 1576548844422,
              "value": "function(ctx, width, height){\n          const size = 100,\n            x = (width - size) / 2,\n            y = (height - size) / 2;\n          ctx.fillStyle = \"black\";\n          ctx.fillRect(x, y, size, size);\n        }",
              "attrs": { "padding": 10 }
            }
          ]
        }
      ]
    }
  ],
  "selectedArributeId": 1,
  "attributeVars": [
    { "id": 1, "type": "color", "value": "#111111", "name": "标题颜色" },
    { "id": 2, "type": "number", "value": 150, "name": "一级标题字体" }
  ],
  "selectedPanel": 0
}
